createintegration/__init__.py
createintegration/create_integration.py
createintegration-0.0.1.dist-info/LICENSE.txt
createintegration-0.0.1.dist-info/METADATA
createintegration-0.0.1.dist-info/WHEEL
createintegration-0.0.1.dist-info/entry_points.txt
createintegration-0.0.1.dist-info/top_level.txt
createintegration-0.0.1.dist-info/RECORD
