Metadata-Version: 2.1
Name: createintegration
Version: 0.0.1
Summary: Create new integrations
Home-page: UNKNOWN
Author: Adnan
Author-email: UNKNOWN
License: UNKNOWN
Platform: UNKNOWN
